xzrr/Xzrr.py
xzrr/__init__.py
xzrr-1.2.dist-info/LICENSE
xzrr-1.2.dist-info/METADATA
xzrr-1.2.dist-info/WHEEL
xzrr-1.2.dist-info/top_level.txt
xzrr-1.2.dist-info/RECORD
